fraudrecord/hash.py
fraudrecord/model.py
fraudrecord/query/__init__.py
fraudrecord/query/cli.py
fraudrecord/query_aio/__init__.py
fraudrecord-2022.10.22.dist-info/entry_points.txt
fraudrecord-2022.10.22.dist-info/LICENSE.txt
fraudrecord-2022.10.22.dist-info/WHEEL
fraudrecord-2022.10.22.dist-info/METADATA
fraudrecord-2022.10.22.dist-info/RECORD
