Metadata-Version: 2.1
Name: fraudrecord
Version: 2022.10.22
Summary: FraudRecord API client
Home-page: https://github.com/yanalunaterra/fraudrecord-python
License: BSD-2-Clause-Patent
Author: Yana Luna-Terra
Author-email: yana@riseup.net
Requires-Python: >=3.10,<4.0
Classifier: License :: OSI Approved
Classifier: Programming Language :: Python :: 3
Classifier: Programming Language :: Python :: 3.10
Classifier: Programming Language :: Python :: 3.11
Classifier: Topic :: Internet :: WWW/HTTP
Provides-Extra: aio
Requires-Dist: aiohttp (>=3.8,<4.0); extra == "aio"
Requires-Dist: pydantic (>=1.10,<2.0)
Project-URL: Repository, https://github.com/yanalunaterra/fraudrecord-python
